{"cameraMode":{"drawMode":0,"name":"Shaded","section":"Shading Mode"},"sceneLighting":false,"audioPlay":false,"sceneViewState":{"m_AlwaysRefresh":false,"showFog":true,"showSkybox":false,"showFlares":true,"showImageEffects":true,"showParticleSystems":true,"showVisualEffectGraphs":true,"m_FxEnabled":false},"in2DMode":false,"pivot":{"x":1.3073310852050782,"y":-0.7965507507324219,"z":-2.968752861022949},"rotation":{"x":-0.1375499814748764,"y":0.013371261768043042,"z":0.0018570335814729334,"w":0.9904032945632935},"size":10.0,"orthographic":true}